powerspot/__init__.py
powerspot/cli.py
powerspot/io.py
powerspot/operations.py
powerspot/ui.py
powerspot-0.2.dist-info/LICENSE
powerspot-0.2.dist-info/METADATA
powerspot-0.2.dist-info/WHEEL
powerspot-0.2.dist-info/entry_points.txt
powerspot-0.2.dist-info/top_level.txt
powerspot-0.2.dist-info/RECORD
