Metadata-Version: 2.1
Name: powerspot
Version: 0.2
Summary: CLI for automated operations with Spotify
Home-page: https://github.com/theodcr/powerspot
Author: "Théo Delecour"
Author-email: "theo.delecour@gmail.com"
License: MIT
Platform: UNKNOWN
Classifier: License :: OSI Approved :: MIT License
Classifier: Programming Language :: Python :: 3.6
Classifier: Programming Language :: Python :: 3.7
Requires-Python: >=3.6
Requires-Dist: Click
Requires-Dist: tabulate
Requires-Dist: spotipy
Provides-Extra: dev
Requires-Dist: black ; extra == 'dev'
Requires-Dist: flake8 ; extra == 'dev'
Requires-Dist: isort ; extra == 'dev'
